gizio/__about__.py
gizio/__init__.py
gizio/core.py
gizio/spec.py
gizio-0.1.0.dist-info/AUTHORS.md
gizio-0.1.0.dist-info/LICENSE
gizio-0.1.0.dist-info/METADATA
gizio-0.1.0.dist-info/WHEEL
gizio-0.1.0.dist-info/top_level.txt
gizio-0.1.0.dist-info/RECORD
