Metadata-Version: 2.1
Name: gizio
Version: 0.1.0
Summary: A light-weight Python package for GIZMO snapshot IO
Home-page: https://gizio.readthedocs.io
Author: gizio developers
License: UNKNOWN
Platform: UNKNOWN
Classifier: Intended Audience :: Science/Research
Classifier: License :: OSI Approved :: MIT License
Classifier: Operating System :: OS Independent
Classifier: Programming Language :: Python :: 3
Classifier: Programming Language :: Python :: 3.6
Classifier: Programming Language :: Python :: 3.7
Classifier: Programming Language :: Python :: 3 :: Only
Classifier: Topic :: Scientific/Engineering
Requires-Python: >=3.6
Requires-Dist: astropy
Requires-Dist: h5py
Requires-Dist: numpy
Requires-Dist: unyt
